semiwrap/__init__.py
semiwrap/__main__.py
semiwrap/casters.py
semiwrap/depfile.py
semiwrap/hooks.py
semiwrap/makeplan.py
semiwrap/mkpc.py
semiwrap/pkgconf_cache.py
semiwrap/pyproject.py
semiwrap/render_meson.py
semiwrap/semiwrap.pc
semiwrap/semiwrap.pybind11.json
semiwrap/util.py
semiwrap/version.py
semiwrap/autowrap/__init__.py
semiwrap/autowrap/buffer.py
semiwrap/autowrap/context.py
semiwrap/autowrap/cxxparser.py
semiwrap/autowrap/generator_data.py
semiwrap/autowrap/mangle.py
semiwrap/autowrap/render_cls_prologue.py
semiwrap/autowrap/render_cls_trampoline_hpp.py
semiwrap/autowrap/render_pybind11.py
semiwrap/autowrap/render_tmpl_inst.py
semiwrap/autowrap/render_wrapped.py
semiwrap/cmd/__init__.py
semiwrap/cmd/dat2cpp.py
semiwrap/cmd/dat2tmplcpp.py
semiwrap/cmd/dat2tmplhpp.py
semiwrap/cmd/dat2trampoline.py
semiwrap/cmd/gen_libinit.py
semiwrap/cmd/gen_modinit_hpp.py
semiwrap/cmd/gen_pkgconf.py
semiwrap/cmd/header2dat.py
semiwrap/cmd/make_pyi.py
semiwrap/cmd/publish_casters.py
semiwrap/cmd/resolve_casters.py
semiwrap/config/__init__.py
semiwrap/config/autowrap_yml.py
semiwrap/config/pyproject_toml.py
semiwrap/config/util.py
semiwrap/include/gilsafe_object.h
semiwrap/include/pybind11_typing.h
semiwrap/include/semiwrap.h
semiwrap/tool/__init__.py
semiwrap/tool/__main__.py
semiwrap/tool/build_dep.py
semiwrap/tool/create_imports.py
semiwrap/tool/scan_headers.py
semiwrap/tool/update_yaml.py
semiwrap-0.2.6.dist-info/METADATA
semiwrap-0.2.6.dist-info/WHEEL
semiwrap-0.2.6.dist-info/entry_points.txt
semiwrap-0.2.6.dist-info/licenses/LICENSE.txt
semiwrap-0.2.6.dist-info/RECORD
