Metadata-Version: 2.4
Name: semiwrap
Version: 0.2.6
Summary: Semi-automated tool to wrap C++ code for use by python
Project-URL: Source code, https://github.com/robotpy/semiwrap
Author-email: Dustin Spicuzza <robotpy@googlegroups.com>
License-Expression: BSD-3-Clause
License-File: LICENSE.txt
Classifier: Development Status :: 5 - Production/Stable
Classifier: Intended Audience :: Developers
Classifier: License :: OSI Approved :: BSD License
Classifier: Programming Language :: Python :: 3 :: Only
Classifier: Topic :: Software Development
Requires-Python: >=3.8
Requires-Dist: cxxheaderparser[pcpp]~=1.7
Requires-Dist: dictdiffer
Requires-Dist: packaging
Requires-Dist: pkgconf
Requires-Dist: pybind11-stubgen~=2.5.1
Requires-Dist: pybind11~=3.0.1
Requires-Dist: pyyaml>=5.1
Requires-Dist: ruamel-yaml~=0.18.16
Requires-Dist: sphinxify>=0.7.3
Requires-Dist: tomli
Requires-Dist: tomli-w
Requires-Dist: toposort
Requires-Dist: typing-extensions
Requires-Dist: validobj~=1.3.0
